LICENSE
MANIFEST.in
README.rst
setup.py
stdeb.cfg
tests.py
starterpyth/__init__.py
starterpyth/cliforms.py
starterpyth/core.py
starterpyth/log.py
starterpyth/model.py
starterpyth/models.py
starterpyth/plugin.py
starterpyth/translation.py
starterpyth/utils.py
starterpyth.egg-info/PKG-INFO
starterpyth.egg-info/SOURCES.txt
starterpyth.egg-info/dependency_links.txt
starterpyth.egg-info/entry_points.txt
starterpyth.egg-info/requires.txt
starterpyth.egg-info/top_level.txt
starterpyth.egg-info/zip-safe
starterpyth/commands/__init__.py
starterpyth/commands/compilemessages.py
starterpyth/commands/dependencies.py
starterpyth/commands/doc_test.py
starterpyth/commands/gen_doc.py
starterpyth/commands/gen_doc_api.py
starterpyth/commands/lint.py
starterpyth/commands/makemessages.py
starterpyth/commands/profiling.py
starterpyth/commands/pseudo_l10n.py
starterpyth/commands/templates/index.rst_tpl
starterpyth/commands/templates/lang.po
starterpyth/commands/templates/module.rst_tpl
starterpyth/data/licenses/APSL.txt
starterpyth/data/licenses/Apache-2.txt
starterpyth/data/licenses/BSD-2-clauses.txt
starterpyth/data/licenses/CeCILL-A.txt
starterpyth/data/licenses/CeCILL-B.txt
starterpyth/data/licenses/CeCILL-C.txt
starterpyth/data/licenses/GPL-2.txt
starterpyth/data/licenses/GPL-3.txt
starterpyth/data/licenses/LGPL-2.txt
starterpyth/data/licenses/LGPL-3.txt
starterpyth/data/licenses/MIT.txt
starterpyth/data/licenses/PSFL.txt
starterpyth/plugins/__init__.py
starterpyth/plugins/base/__init__.py
starterpyth/plugins/base/templates/VERSION_tpl
starterpyth/plugins/base/templates/ez_setup.py_tpl
starterpyth/plugins/base/templates/setup.py_tpl
starterpyth/plugins/starter_cython/__init__.py
starterpyth/plugins/starter_cython/extra_templates/setup.py_tpl
starterpyth/plugins/starter_cython/templates/doc/source/externals/cython_0.19.inv
starterpyth/plugins/starter_cython/templates/{{module_name}}/sample_cython.pyx_tpl
starterpyth/plugins/starter_cython/templates/{{module_name}}/tests/test_cython.py_tpl
starterpyth/templates/cli/run.py_tpl
starterpyth/templates/cli/{{module_name}}/cli.py_tpl
starterpyth/templates/common/.gitignore
starterpyth/templates/common/LICENSE_tpl
starterpyth/templates/common/MANIFEST.in_tpl
