Metadata-Version: 1.0
Name: starterpyth
Version: 1.5.14
Summary: Generate skeletons for new Python applications.
Home-page: http://www.19pouces.net/projects.html
Author: Matthieu Gallet
Author-email: github@19pouces.net
License: Cecill-B
Platform: UNKNOWN
